sightengine/__init__.py
sightengine/check.py
sightengine/client.py
sightengine-1.3.0.dist-info/DESCRIPTION.rst
sightengine-1.3.0.dist-info/METADATA
sightengine-1.3.0.dist-info/RECORD
sightengine-1.3.0.dist-info/WHEEL
sightengine-1.3.0.dist-info/metadata.json
sightengine-1.3.0.dist-info/top_level.txt
