Metadata-Version: 2.0
Name: sightengine
Version: 1.3.0
Summary: Sightengine Python client
Home-page: https://github.com/Sightengine/client-python
Author: Sightengine
Author-email: support@sightengine.com
License: UNKNOWN
Platform: UNKNOWN
